flexible_inspect_py-2.0.0.dist-info/METADATA
flexible_inspect_py-2.0.0.dist-info/WHEEL
flexible_inspect_py-2.0.0.dist-info/license_files/LICENSE
flexible_inspect_py/__init__.py
flexible_inspect_py/__init__.pyi
flexible_inspect_py/py.typed
flexible_inspect_py/flexible_inspect_py.abi3.so
flexible_inspect_py-2.0.0.dist-info/RECORD
