Metadata-Version: 2.1
Name: flexible_inspect_py
Version: 2.0.0
Classifier: Programming Language :: Rust
Classifier: Programming Language :: Python :: Implementation :: CPython
Classifier: License :: OSI Approved :: MIT License
Classifier: Programming Language :: Python :: Implementation :: PyPy
License-File: LICENSE
Summary: Library for creating a custom validator
Keywords: validate,regex,rust
Author: Mansur Azatbek
Author-email: mansur62624@gmail.com
License: MIT
Requires-Python: >=3.7
Project-URL: Homepage, https://github.com/m62624/pystval
